LICENSE
MANIFEST.in
README.MD
README.md
setup.py
libpythonprodaanrod/__init__.py
libpythonprodaanrod/github_api.py
libpythonprodaanrod.egg-info/PKG-INFO
libpythonprodaanrod.egg-info/SOURCES.txt
libpythonprodaanrod.egg-info/dependency_links.txt
libpythonprodaanrod.egg-info/not-zip-safe
libpythonprodaanrod.egg-info/requires.txt
libpythonprodaanrod.egg-info/top_level.txt
libpythonprodaanrod/spam/__init__.py
libpythonprodaanrod/spam/db.py
libpythonprodaanrod/spam/enviador_de_email.py
libpythonprodaanrod/spam/main.py
libpythonprodaanrod/spam/modelos.py
libpythonprodaanrod/tests/__init__.py
libpythonprodaanrod/tests/test_exemplo.py
libpythonprodaanrod/tests/test_spam/__init__.py
libpythonprodaanrod/tests/test_spam/conftest.py
libpythonprodaanrod/tests/test_spam/test_enviador_de_email.py
libpythonprodaanrod/tests/test_spam/test_envio_para_base_de_usuarios.py
libpythonprodaanrod/tests/test_spam/test_usuarios.py